wapi2nsconf/__init__.py
wapi2nsconf/cli.py
wapi2nsconf/config.py
wapi2nsconf/utils.py
wapi2nsconf/wapi.py
wapi2nsconf/templates/bind.conf
wapi2nsconf/templates/knot.conf
wapi2nsconf/templates/nsd.conf
wapi2nsconf/templates/zones.json.j2
wapi2nsconf/templates/zones.yaml.j2
wapi2nsconf-0.6.0.dist-info/METADATA
wapi2nsconf-0.6.0.dist-info/WHEEL
wapi2nsconf-0.6.0.dist-info/entry_points.txt
wapi2nsconf-0.6.0.dist-info/licenses/LICENSE
wapi2nsconf-0.6.0.dist-info/RECORD
