Metadata-Version: 2.4
Name: wapi2nsconf
Version: 0.6.0
Summary: Infoblox WAPI to DNS server configuration tool
Project-URL: repository, https://github.com/kirei/wapi2nsconf
Author-email: Jakob Schlyter <jakob@kirei.se>
License-Expression: BSD-2-Clause
License-File: LICENSE
Requires-Python: <4.0,>=3.11
Requires-Dist: httpx>=0.28.1
Requires-Dist: jinja2>=3.0.3
Requires-Dist: pydantic>=2.12.4
Requires-Dist: pyyaml>=6
